icutk/__init__.py
icutk/cli.py
icutk/lex.py
icutk/log.py
icutk/obj.py
icutk/path.py
icutk/string.py
icutk/subproc.py
icutk/time.py
icutk-0.3.7.dist-info/LICENSE
icutk-0.3.7.dist-info/METADATA
icutk-0.3.7.dist-info/WHEEL
icutk-0.3.7.dist-info/top_level.txt
icutk-0.3.7.dist-info/RECORD
